taskstats.py
taskstats-0.0.3.dist-info/LICENSE
taskstats-0.0.3.dist-info/METADATA
taskstats-0.0.3.dist-info/WHEEL
taskstats-0.0.3.dist-info/top_level.txt
taskstats-0.0.3.dist-info/RECORD
